itinerary/__init__.py
itinerary/repo.py
itinerary/utils.py
places/__init__.py
places/__version__.py
places/client.py
places/models.py
system_toolbox-0.0.4.dist-info/METADATA
system_toolbox-0.0.4.dist-info/WHEEL
system_toolbox-0.0.4.dist-info/top_level.txt
system_toolbox-0.0.4.dist-info/RECORD
